Protocols/DMA-AXI-Project/src/axi_full_slave.v

module axi_full_slave #(
    parameter ADDR_WIDTH = 32,
    parameter DATA_WIDTH = 32,
    parameter ID_WIDTH   = 4,
    parameter STRB_WIDTH = DATA_WIDTH / 8,
    parameter MEM_WORDS  = 4096
) (
    input wire clk,
    input wire rst_n,


    input  wire [ADDR_WIDTH-1:0] s_axi_awaddr,
    input  wire [           7:0] s_axi_awlen,
    input  wire [           2:0] s_axi_awsize,
    input  wire [           1:0] s_axi_awburst,
    input  wire [  ID_WIDTH-1:0] s_axi_awid,
    input  wire                  s_axi_awvalid,
    output wire                  s_axi_awready,


    input  wire [DATA_WIDTH-1:0] s_axi_wdata,
    input  wire [STRB_WIDTH-1:0] s_axi_wstrb,
    input  wire                  s_axi_wlast,
    input  wire                  s_axi_wvalid,
    output wire                  s_axi_wready,


    output wire [         1:0] s_axi_bresp,
    output wire [ID_WIDTH-1:0] s_axi_bid,
    output wire                s_axi_bvalid,
    input  wire                s_axi_bready,


    input  wire [ADDR_WIDTH-1:0] s_axi_araddr,
    input  wire [           7:0] s_axi_arlen,
    input  wire [           2:0] s_axi_arsize,
    input  wire [           1:0] s_axi_arburst,
    input  wire [  ID_WIDTH-1:0] s_axi_arid,
    input  wire                  s_axi_arvalid,
    output wire                  s_axi_arready,


    output wire [DATA_WIDTH-1:0] s_axi_rdata,
    output wire [           1:0] s_axi_rresp,
    output wire [  ID_WIDTH-1:0] s_axi_rid,
    output wire                  s_axi_rlast,
    output wire                  s_axi_rvalid,
    input  wire                  s_axi_rready
);

  localparam S_IDLE = 2'd0;
  localparam S_WDATA = 2'd1;
  localparam S_WRESP = 2'd2;
  localparam S_RDATA = 2'd3;

  localparam [1:0] RESP_OKAY = 2'b00;
  localparam [1:0] RESP_SLVERR = 2'b10;

  reg [1:0] state, next_state;

  reg [ADDR_WIDTH-1:0] cur_waddr, cur_raddr;
  reg [7:0] awlen_reg, arlen_reg;
  reg [7:0] wbeat_cnt, rbeat_cnt;
  reg [ID_WIDTH-1:0] awid_reg, arid_reg;
  reg                  werror_reg;

  reg [DATA_WIDTH-1:0] mem        [0:MEM_WORDS-1];


  assign s_axi_awready = (state == S_IDLE);
  assign s_axi_arready = (state == S_IDLE) && !s_axi_awvalid;

  wire aw_hs = s_axi_awvalid && s_axi_awready;
  wire ar_hs = s_axi_arvalid && s_axi_arready;
  wire w_hs = s_axi_wvalid && s_axi_wready;
  wire b_hs = s_axi_bvalid && s_axi_bready;
  wire r_hs = s_axi_rvalid && s_axi_rready;

  always @(posedge clk) begin
    if (!rst_n) state <= S_IDLE;
    else state <= next_state;
  end

  always @(*) begin
    next_state = state;
    case (state)
      S_IDLE: begin
        if (aw_hs) next_state = S_WDATA;
        else if (ar_hs) next_state = S_RDATA;
      end
      S_WDATA: if (w_hs && s_axi_wlast) next_state = S_WRESP;
      S_WRESP: if (b_hs) next_state = S_IDLE;
      S_RDATA: if (r_hs && (rbeat_cnt == arlen_reg)) next_state = S_IDLE;
      default: next_state = S_IDLE;
    endcase
  end


  integer bi;
  reg [DATA_WIDTH-1:0] wmask_data;
  always @(*) begin
    wmask_data = mem[cur_waddr>>2];
    for (bi = 0; bi < STRB_WIDTH; bi = bi + 1) begin
      if (s_axi_wstrb[bi]) wmask_data[bi*8+:8] = s_axi_wdata[bi*8+:8];
    end
  end


  always @(posedge clk) begin
    if (!rst_n) begin
      cur_waddr  <= {ADDR_WIDTH{1'b0}};
      cur_raddr  <= {ADDR_WIDTH{1'b0}};
      awlen_reg  <= 8'd0;
      arlen_reg  <= 8'd0;
      wbeat_cnt  <= 8'd0;
      rbeat_cnt  <= 8'd0;
      awid_reg   <= {ID_WIDTH{1'b0}};
      arid_reg   <= {ID_WIDTH{1'b0}};
      werror_reg <= 1'b0;
    end else begin
      if (aw_hs) begin
        cur_waddr  <= s_axi_awaddr;
        awlen_reg  <= s_axi_awlen;
        awid_reg   <= s_axi_awid;
        wbeat_cnt  <= 8'd0;
        werror_reg <= 1'b0;
      end else if (ar_hs) begin
        cur_raddr <= s_axi_araddr;
        arlen_reg <= s_axi_arlen;
        arid_reg  <= s_axi_arid;
        rbeat_cnt <= 8'd0;
      end else if (w_hs) begin
        if ((cur_waddr >> 2) < MEM_WORDS) begin
          mem[cur_waddr>>2] <= wmask_data;
        end else begin
          werror_reg <= 1'b1;
        end
        cur_waddr <= cur_waddr + 4;
        wbeat_cnt <= wbeat_cnt + 1'b1;
      end else if (r_hs) begin
        cur_raddr <= cur_raddr + 4;
        rbeat_cnt <= rbeat_cnt + 1'b1;
      end
    end
  end


  assign s_axi_wready = (state == S_WDATA);
  assign s_axi_bvalid = (state == S_WRESP);
  assign s_axi_bresp  = werror_reg ? RESP_SLVERR : RESP_OKAY;
  assign s_axi_bid    = awid_reg;


  wire raddr_in_range = ((cur_raddr >> 2) < MEM_WORDS);
  assign s_axi_rvalid = (state == S_RDATA);
  assign s_axi_rdata  = raddr_in_range ? mem[cur_raddr >> 2] : {DATA_WIDTH{1'b0}};
  assign s_axi_rresp  = raddr_in_range ? RESP_OKAY : RESP_SLVERR;
  assign s_axi_rlast  = (state == S_RDATA) && (rbeat_cnt == arlen_reg);
  assign s_axi_rid    = arid_reg;

endmodule

Protocols/DMA-AXI-Project/src/axi_full_master.v


module axi_full_master #(
    parameter ADDR_WIDTH = 32,
    parameter DATA_WIDTH = 32,
    parameter ID_WIDTH   = 4,
    parameter STRB_WIDTH = DATA_WIDTH / 8
) (
    input wire clk,
    input wire rst_n,

    input wire                  start_write,
    input wire                  start_read,
    input wire [ADDR_WIDTH-1:0] m_addr,
    input wire [           7:0] m_len,

    output reg  write_done,
    output reg  read_done,
    output reg  m_error,
    output wire master_busy,

    input  wire                  wdata_valid,
    input  wire [DATA_WIDTH-1:0] wdata,
    input  wire [STRB_WIDTH-1:0] wstrb,
    output wire                  wdata_ready,

    output wire                  rdata_valid,
    output wire [DATA_WIDTH-1:0] rdata,
    output wire                  rdata_last,
    input  wire                  rdata_ready,

    output wire [ADDR_WIDTH-1:0] m_axi_awaddr,
    output wire [           7:0] m_axi_awlen,
    output wire [           2:0] m_axi_awsize,
    output wire [           1:0] m_axi_awburst,
    output wire [  ID_WIDTH-1:0] m_axi_awid,
    output wire                  m_axi_awvalid,
    input  wire                  m_axi_awready,

    output wire [DATA_WIDTH-1:0] m_axi_wdata,
    output wire [STRB_WIDTH-1:0] m_axi_wstrb,
    output wire                  m_axi_wlast,
    output wire                  m_axi_wvalid,
    input  wire                  m_axi_wready,

    input  wire [1:0] m_axi_bresp,
    input  wire       m_axi_bvalid,
    output wire       m_axi_bready,

    output wire [ADDR_WIDTH-1:0] m_axi_araddr,
    output wire [           7:0] m_axi_arlen,
    output wire [           2:0] m_axi_arsize,
    output wire [           1:0] m_axi_arburst,
    output wire [  ID_WIDTH-1:0] m_axi_arid,
    output wire                  m_axi_arvalid,
    input  wire                  m_axi_arready,

    input  wire [DATA_WIDTH-1:0] m_axi_rdata,
    input  wire [           1:0] m_axi_rresp,
    input  wire                  m_axi_rlast,
    input  wire                  m_axi_rvalid,
    output wire                  m_axi_rready
);

  localparam       S_IDLE     = 3'd0;
  localparam       S_AW       = 3'd1;
  localparam       S_WDATA    = 3'd2;
  localparam       S_BRESP    = 3'd3;
  localparam       S_AR       = 3'd4;
  localparam       S_RDATA    = 3'd5;

  localparam [1:0] BURST_INCR = 2'b01;
  localparam [2:0] SIZE_4B    = 3'b010;

  reg [2:0] state, next_state;

  reg [ADDR_WIDTH-1:0] awaddr_reg, araddr_reg;
  reg [7:0] awlen_reg, arlen_reg;
  reg [7:0] wbeat_cnt;



  always @(posedge clk) begin
    if (!rst_n) state <= S_IDLE;
    else state <= next_state;
  end

  wire aw_hs = m_axi_awvalid && m_axi_awready;
  wire w_hs = m_axi_wvalid && m_axi_wready;
  wire b_hs = m_axi_bvalid && m_axi_bready;
  wire ar_hs = m_axi_arvalid && m_axi_arready;
  wire r_hs = m_axi_rvalid && m_axi_rready;

  always @(*) begin
    next_state = state;
    case (state)
      S_IDLE: begin
        if (start_write) next_state = S_AW;
        else if (start_read) next_state = S_AR;
      end
      S_AW:    if (aw_hs) next_state = S_WDATA;
      S_WDATA: if (w_hs && m_axi_wlast) next_state = S_BRESP;
      S_BRESP: if (b_hs) next_state = S_IDLE;
      S_AR:    if (ar_hs) next_state = S_RDATA;
      S_RDATA: if (r_hs && m_axi_rlast) next_state = S_IDLE;
      default: next_state = S_IDLE;
    endcase
  end

  assign master_busy = (state != S_IDLE);


  always @(posedge clk) begin
    if (!rst_n) begin
      awaddr_reg <= {ADDR_WIDTH{1'b0}};
      awlen_reg  <= 8'd0;
      araddr_reg <= {ADDR_WIDTH{1'b0}};
      arlen_reg  <= 8'd0;
      wbeat_cnt  <= 8'd0;
    end else begin
      if (state == S_IDLE && start_write) begin
        awaddr_reg <= m_addr;
        awlen_reg  <= m_len;
        wbeat_cnt  <= 8'd0;
      end else if (state == S_IDLE && start_read) begin
        araddr_reg <= m_addr;
        arlen_reg  <= m_len;
      end else if (w_hs) begin
        wbeat_cnt <= wbeat_cnt + 1'b1;
      end
    end
  end


  assign m_axi_awaddr  = awaddr_reg;
  assign m_axi_awlen   = awlen_reg;
  assign m_axi_awsize  = SIZE_4B;
  assign m_axi_awburst = BURST_INCR;
  assign m_axi_awid    = {ID_WIDTH{1'b0}};
  assign m_axi_awvalid = (state == S_AW);

  assign m_axi_wdata   = wdata;
  assign m_axi_wstrb   = wstrb;
  assign m_axi_wlast   = (state == S_WDATA) && (wbeat_cnt == awlen_reg);
  assign m_axi_wvalid  = (state == S_WDATA) && wdata_valid;
  assign wdata_ready   = (state == S_WDATA) && m_axi_wready;

  assign m_axi_bready  = (state == S_BRESP);

  assign m_axi_araddr  = araddr_reg;
  assign m_axi_arlen   = arlen_reg;
  assign m_axi_arsize  = SIZE_4B;
  assign m_axi_arburst = BURST_INCR;
  assign m_axi_arid    = {ID_WIDTH{1'b0}};
  assign m_axi_arvalid = (state == S_AR);

  assign m_axi_rready  = (state == S_RDATA) && rdata_ready;
  assign rdata_valid   = (state == S_RDATA) && m_axi_rvalid;
  assign rdata         = m_axi_rdata;
  assign rdata_last    = m_axi_rlast;


  always @(posedge clk) begin
    if (!rst_n) begin
      write_done <= 1'b0;
      read_done  <= 1'b0;
      m_error    <= 1'b0;
    end else begin
      write_done <= 1'b0;
      read_done  <= 1'b0;

      if (state == S_IDLE && (start_write || start_read)) m_error <= 1'b0;

      if (state == S_BRESP && b_hs) begin
        write_done <= 1'b1;
        if (m_axi_bresp != 2'b00) m_error <= 1'b1;
      end

      if (state == S_RDATA && r_hs && m_axi_rlast) begin
        read_done <= 1'b1;
        if (m_axi_rresp != 2'b00) m_error <= 1'b1;
      end
    end
  end

endmodule

Protocols/DMA-AXI-Project/src/tb_axi_full.v

`timescale 1ns / 1ps

module tb_axi_full;

  localparam ADDR_WIDTH = 32;
  localparam DATA_WIDTH = 32;
  localparam ID_WIDTH   = 4;
  localparam STRB_WIDTH = DATA_WIDTH / 8;

  reg clk, rst_n;

  reg start_write, start_read;
  reg [ADDR_WIDTH-1:0] m_addr;
  reg [           7:0] m_len;
  wire write_done, read_done, m_error, master_busy;

  reg                   wdata_valid;
  reg  [DATA_WIDTH-1:0] wdata;
  reg  [STRB_WIDTH-1:0] wstrb;
  wire                  wdata_ready;

  wire                  rdata_valid;
  wire [DATA_WIDTH-1:0] rdata;
  wire                  rdata_last;
  reg                   rdata_ready;

  wire [ADDR_WIDTH-1:0] awaddr;
  wire [           7:0] awlen;
  wire [           2:0] awsize;
  wire [           1:0] awburst;
  wire [  ID_WIDTH-1:0] awid;
  wire awvalid, awready;

  wire [DATA_WIDTH-1:0] wdata_bus;
  wire [STRB_WIDTH-1:0] wstrb_bus;
  wire wlast, wvalid, wready;

  wire [1:0] bresp;
  wire [ID_WIDTH-1:0] bid;
  wire bvalid, bready;

  wire [ADDR_WIDTH-1:0] araddr;
  wire [7:0] arlen;
  wire [2:0] arsize;
  wire [1:0] arburst;
  wire [ID_WIDTH-1:0] arid;
  wire arvalid, arready;

  wire [DATA_WIDTH-1:0] rdata_bus;
  wire [1:0] rresp;
  wire [ID_WIDTH-1:0] rid;
  wire rlast, rvalid, rready;

  axi_full_master #(
      .ADDR_WIDTH(ADDR_WIDTH),
      .DATA_WIDTH(DATA_WIDTH),
      .ID_WIDTH  (ID_WIDTH)
  ) u_master (
      .clk(clk),
      .rst_n(rst_n),
      .start_write(start_write),
      .start_read(start_read),
      .m_addr(m_addr),
      .m_len(m_len),
      .write_done(write_done),
      .read_done(read_done),
      .m_error(m_error),
      .master_busy(master_busy),
      .wdata_valid(wdata_valid),
      .wdata(wdata),
      .wstrb(wstrb),
      .wdata_ready(wdata_ready),
      .rdata_valid(rdata_valid),
      .rdata(rdata),
      .rdata_last(rdata_last),
      .rdata_ready(rdata_ready),
      .m_axi_awaddr(awaddr),
      .m_axi_awlen(awlen),
      .m_axi_awsize(awsize),
      .m_axi_awburst(awburst),
      .m_axi_awid(awid),
      .m_axi_awvalid(awvalid),
      .m_axi_awready(awready),
      .m_axi_wdata(wdata_bus),
      .m_axi_wstrb(wstrb_bus),
      .m_axi_wlast(wlast),
      .m_axi_wvalid(wvalid),
      .m_axi_wready(wready),
      .m_axi_bresp(bresp),
      .m_axi_bvalid(bvalid),
      .m_axi_bready(bready),
      .m_axi_araddr(araddr),
      .m_axi_arlen(arlen),
      .m_axi_arsize(arsize),
      .m_axi_arburst(arburst),
      .m_axi_arid(arid),
      .m_axi_arvalid(arvalid),
      .m_axi_arready(arready),
      .m_axi_rdata(rdata_bus),
      .m_axi_rresp(rresp),
      .m_axi_rlast(rlast),
      .m_axi_rvalid(rvalid),
      .m_axi_rready(rready)
  );

  axi_full_slave #(
      .ADDR_WIDTH(ADDR_WIDTH),
      .DATA_WIDTH(DATA_WIDTH),
      .ID_WIDTH  (ID_WIDTH),
      .MEM_WORDS (1024)
  ) u_slave (
      .clk(clk),
      .rst_n(rst_n),
      .s_axi_awaddr(awaddr),
      .s_axi_awlen(awlen),
      .s_axi_awsize(awsize),
      .s_axi_awburst(awburst),
      .s_axi_awid(awid),
      .s_axi_awvalid(awvalid),
      .s_axi_awready(awready),
      .s_axi_wdata(wdata_bus),
      .s_axi_wstrb(wstrb_bus),
      .s_axi_wlast(wlast),
      .s_axi_wvalid(wvalid),
      .s_axi_wready(wready),
      .s_axi_bresp(bresp),
      .s_axi_bid(bid),
      .s_axi_bvalid(bvalid),
      .s_axi_bready(bready),
      .s_axi_araddr(araddr),
      .s_axi_arlen(arlen),
      .s_axi_arsize(arsize),
      .s_axi_arburst(arburst),
      .s_axi_arid(arid),
      .s_axi_arvalid(arvalid),
      .s_axi_arready(arready),
      .s_axi_rdata(rdata_bus),
      .s_axi_rresp(rresp),
      .s_axi_rid(rid),
      .s_axi_rlast(rlast),
      .s_axi_rvalid(rvalid),
      .s_axi_rready(rready)
  );

  initial clk = 0;
  always #5 clk = ~clk;

  integer errors = 0;



  task automatic axi_write_burst(input [31:0] base_addr, input [7:0] len_beats,
                                 input [31:0] base_data);
    integer i;
    begin
      @(posedge clk);
      m_addr      = base_addr;
      m_len       = len_beats - 1;
      start_write = 1'b1;
      @(posedge clk);
      start_write = 1'b0;

      i = 0;
      while (i < len_beats) begin
        wdata_valid = 1'b1;
        wdata       = base_data + i;
        wstrb       = 4'hF;
        @(posedge clk);
        if (wdata_valid && wdata_ready) i = i + 1;
      end
      wdata_valid = 1'b0;

      wait (write_done == 1'b1);
      @(posedge clk);
    end
  endtask






  task automatic axi_read_burst(input [31:0] base_addr, input [7:0] len_beats,
                                input [31:0] base_data);
    integer i;
    reg [31:0] got;
    begin
      @(posedge clk);
      m_addr     = base_addr;
      m_len      = len_beats - 1;
      start_read = 1'b1;
      @(posedge clk);
      start_read = 1'b0;

      i = 0;
      rdata_ready = 1'b1;
      while (i < len_beats) begin
        @(posedge clk);
        if (rdata_valid && rdata_ready) begin
          got = rdata;
          if (got !== (base_data + i)) begin
            $display("MISMATCH burst %0d: got %h expected %h", i, got, base_data + i);
            errors = errors + 1;
          end else begin
            $display("MATCH burst %0d: got %h expected %h", i, got, base_data + i);
          end

          if ((i == len_beats - 1) && !rdata_last) begin
            $display("ERROR RLAST not asserted on final burst %0d", i);
            errors = errors + 1;
          end
          i = i + 1;
        end
      end
      rdata_ready = 1'b0;

      wait (read_done == 1'b1);
      @(posedge clk);
    end
  endtask




  initial begin
    rst_n = 0;
    start_write = 0;
    start_read = 0;
    m_addr = 0;
    m_len = 0;
    wdata_valid = 0;
    wdata = 0;
    wstrb = 4'hF;
    rdata_ready = 0;
    repeat (4) @(posedge clk);
    rst_n = 1;
    repeat (2) @(posedge clk);

    $display("\nBurst length 1");
    axi_write_burst(32'h0000_0000, 8'd1, 32'hAAAA_0000);
    axi_read_burst(32'h0000_0000, 8'd1, 32'hAAAA_0000);

    $display("\nBurst length 4");
    axi_write_burst(32'h0000_0040, 8'd4, 32'hBBBB_0000);
    axi_read_burst(32'h0000_0040, 8'd4, 32'hBBBB_0000);

    $display("\nBurst length 16 (max)");
    axi_write_burst(32'h0000_0100, 8'd16, 32'hCCCC_0000);
    axi_read_burst(32'h0000_0100, 8'd16, 32'hCCCC_0000);

    if (errors == 0) $display("\nALL TESTS PASSED");
    else $display("\n%0d ERROR(S)", errors);

    $finish;
  end

  initial begin
    $dumpfile("tb_axi_full.vcd");
    $dumpvars(0, tb_axi_full);
  end

endmodule


// iverilog -o sim_axi_full axi_full_master.v axi_full_slave.v tb_axi_full.v; vvp sim_axi_full

Protocols/DMA-AXI-Project/src/tb_axi_full.vcd
$date
	Sat Aug 29 00:28:09 2026
$end
$version
	Icarus Verilog
$end
$timescale
	1ps
$end
$scope module tb_axi_full $end
$var wire 2 ! arburst [1:0] $end
$var wire 4 " arid [3:0] $end
$var wire 3 # arsize [2:0] $end
$var wire 2 $ awburst [1:0] $end
$var wire 4 % awid [3:0] $end
$var wire 3 & awsize [2:0] $end
$var wire 1 ' wvalid $end
$var wire 4 ( wstrb_bus [3:0] $end
$var wire 1 ) write_done $end
$var wire 1 * wready $end
$var wire 1 + wlast $end
$var wire 1 , wdata_ready $end
$var wire 32 - wdata_bus [31:0] $end
$var wire 1 . rvalid $end
$var wire 2 / rresp [1:0] $end
$var wire 1 0 rready $end
$var wire 1 1 rlast $end
$var wire 4 2 rid [3:0] $end
$var wire 1 3 read_done $end
$var wire 1 4 rdata_valid $end
$var wire 1 5 rdata_last $end
$var wire 32 6 rdata_bus [31:0] $end
$var wire 32 7 rdata [31:0] $end
$var wire 1 8 master_busy $end
$var wire 1 9 m_error $end
$var wire 1 : bvalid $end
$var wire 2 ; bresp [1:0] $end
$var wire 1 < bready $end
$var wire 4 = bid [3:0] $end
$var wire 1 > awvalid $end
$var wire 1 ? awready $end
$var wire 8 @ awlen [7:0] $end
$var wire 32 A awaddr [31:0] $end
$var wire 1 B arvalid $end
$var wire 1 C arready $end
$var wire 8 D arlen [7:0] $end
$var wire 32 E araddr [31:0] $end
$var parameter 32 F ADDR_WIDTH $end
$var parameter 32 G DATA_WIDTH $end
$var parameter 32 H ID_WIDTH $end
$var parameter 32 I STRB_WIDTH $end
$var reg 1 J clk $end
$var reg 32 K m_addr [31:0] $end
$var reg 8 L m_len [7:0] $end
$var reg 1 M rdata_ready $end
$var reg 1 N rst_n $end
$var reg 1 O start_read $end
$var reg 1 P start_write $end
$var reg 32 Q wdata [31:0] $end
$var reg 1 R wdata_valid $end
$var reg 4 S wstrb [3:0] $end
$var integer 32 T errors [31:0] $end
$scope module u_master $end
$var wire 1 U ar_hs $end
$var wire 1 V aw_hs $end
$var wire 1 W b_hs $end
$var wire 1 J clk $end
$var wire 32 X m_addr [31:0] $end
$var wire 32 Y m_axi_araddr [31:0] $end
$var wire 2 Z m_axi_arburst [1:0] $end
$var wire 4 [ m_axi_arid [3:0] $end
$var wire 8 \ m_axi_arlen [7:0] $end
$var wire 3 ] m_axi_arsize [2:0] $end
$var wire 32 ^ m_axi_awaddr [31:0] $end
$var wire 2 _ m_axi_awburst [1:0] $end
$var wire 4 ` m_axi_awid [3:0] $end
$var wire 8 a m_axi_awlen [7:0] $end
$var wire 3 b m_axi_awsize [2:0] $end
$var wire 1 0 m_axi_rready $end
$var wire 32 c m_axi_wdata [31:0] $end
$var wire 1 + m_axi_wlast $end
$var wire 4 d m_axi_wstrb [3:0] $end
$var wire 1 ' m_axi_wvalid $end
$var wire 8 e m_len [7:0] $end
$var wire 1 f r_hs $end
$var wire 32 g rdata [31:0] $end
$var wire 1 5 rdata_last $end
$var wire 1 M rdata_ready $end
$var wire 1 4 rdata_valid $end
$var wire 1 N rst_n $end
$var wire 1 O start_read $end
$var wire 1 P start_write $end
$var wire 1 h w_hs $end
$var wire 32 i wdata [31:0] $end
$var wire 1 , wdata_ready $end
$var wire 1 R wdata_valid $end
$var wire 4 j wstrb [3:0] $end
$var wire 1 8 master_busy $end
$var wire 1 * m_axi_wready $end
$var wire 1 . m_axi_rvalid $end
$var wire 2 k m_axi_rresp [1:0] $end
$var wire 1 1 m_axi_rlast $end
$var wire 32 l m_axi_rdata [31:0] $end
$var wire 1 : m_axi_bvalid $end
$var wire 2 m m_axi_bresp [1:0] $end
$var wire 1 < m_axi_bready $end
$var wire 1 > m_axi_awvalid $end
$var wire 1 ? m_axi_awready $end
$var wire 1 B m_axi_arvalid $end
$var wire 1 C m_axi_arready $end
$var parameter 32 n ADDR_WIDTH $end
$var parameter 2 o BURST_INCR $end
$var parameter 32 p DATA_WIDTH $end
$var parameter 32 q ID_WIDTH $end
$var parameter 3 r SIZE_4B $end
$var parameter 32 s STRB_WIDTH $end
$var parameter 3 t S_AR $end
$var parameter 3 u S_AW $end
$var parameter 3 v S_BRESP $end
$var parameter 3 w S_IDLE $end
$var parameter 3 x S_RDATA $end
$var parameter 3 y S_WDATA $end
$var reg 32 z araddr_reg [31:0] $end
$var reg 8 { arlen_reg [7:0] $end
$var reg 32 | awaddr_reg [31:0] $end
$var reg 8 } awlen_reg [7:0] $end
$var reg 1 9 m_error $end
$var reg 3 ~ next_state [2:0] $end
$var reg 1 3 read_done $end
$var reg 3 !" state [2:0] $end
$var reg 8 "" wbeat_cnt [7:0] $end
$var reg 1 ) write_done $end
$upscope $end
$scope module u_slave $end
$var wire 1 #" ar_hs $end
$var wire 1 $" aw_hs $end
$var wire 1 %" b_hs $end
$var wire 1 J clk $end
$var wire 1 &" r_hs $end
$var wire 1 N rst_n $end
$var wire 32 '" s_axi_araddr [31:0] $end
$var wire 2 (" s_axi_arburst [1:0] $end
$var wire 4 )" s_axi_arid [3:0] $end
$var wire 8 *" s_axi_arlen [7:0] $end
$var wire 1 C s_axi_arready $end
$var wire 3 +" s_axi_arsize [2:0] $end
$var wire 1 B s_axi_arvalid $end
$var wire 32 ," s_axi_awaddr [31:0] $end
$var wire 2 -" s_axi_awburst [1:0] $end
$var wire 4 ." s_axi_awid [3:0] $end
$var wire 8 /" s_axi_awlen [7:0] $end
$var wire 3 0" s_axi_awsize [2:0] $end
$var wire 1 > s_axi_awvalid $end
$var wire 4 1" s_axi_bid [3:0] $end
$var wire 1 < s_axi_bready $end
$var wire 4 2" s_axi_rid [3:0] $end
$var wire 1 1 s_axi_rlast $end
$var wire 1 0 s_axi_rready $end
$var wire 32 3" s_axi_wdata [31:0] $end
$var wire 1 + s_axi_wlast $end
$var wire 4 4" s_axi_wstrb [3:0] $end
$var wire 1 ' s_axi_wvalid $end
$var wire 1 5" w_hs $end
$var wire 1 * s_axi_wready $end
$var wire 1 . s_axi_rvalid $end
$var wire 2 6" s_axi_rresp [1:0] $end
$var wire 32 7" s_axi_rdata [31:0] $end
$var wire 1 : s_axi_bvalid $end
$var wire 2 8" s_axi_bresp [1:0] $end
$var wire 1 ? s_axi_awready $end
$var wire 1 9" raddr_in_range $end
$var parameter 32 :" ADDR_WIDTH $end
$var parameter 32 ;" DATA_WIDTH $end
$var parameter 32 <" ID_WIDTH $end
$var parameter 32 =" MEM_WORDS $end
$var parameter 2 >" RESP_OKAY $end
$var parameter 2 ?" RESP_SLVERR $end
$var parameter 32 @" STRB_WIDTH $end
$var parameter 2 A" S_IDLE $end
$var parameter 2 B" S_RDATA $end
$var parameter 2 C" S_WDATA $end
$var parameter 2 D" S_WRESP $end
$var reg 4 E" arid_reg [3:0] $end
$var reg 8 F" arlen_reg [7:0] $end
$var reg 4 G" awid_reg [3:0] $end
$var reg 8 H" awlen_reg [7:0] $end
$var reg 32 I" cur_raddr [31:0] $end
$var reg 32 J" cur_waddr [31:0] $end
$var reg 2 K" next_state [1:0] $end
$var reg 8 L" rbeat_cnt [7:0] $end
$var reg 2 M" state [1:0] $end
$var reg 8 N" wbeat_cnt [7:0] $end
$var reg 1 O" werror_reg $end
$var reg 32 P" wmask_data [31:0] $end
$var integer 32 Q" bi [31:0] $end
$upscope $end
$scope task axi_read_burst $end
$upscope $end
$scope task axi_write_burst $end
$upscope $end
$upscope $end
$enddefinitions $end
$comment Show the parameter values. $end
$dumpall
b10 D"
b1 C"
b11 B"
b0 A"
b100 @"
b10 ?"
b0 >"
b10000000000 ="
b100 <"
b100000 ;"
b100000 :"
b10 y
b101 x
b0 w
b11 v
b1 u
b100 t
b100 s
b10 r
b100 q
b100000 p
b1 o
b100000 n
b100 I
b100 H
b100000 G
b100000 F
$end
#0
$dumpvars
b100 Q"
b0 P"
xO"
bx N"
bx M"
bx L"
b0 K"
bx J"
bx I"
bx H"
bx G"
bx F"
bx E"
x9"
bx0 8"
bx 7"
bx0 6"
05"
b1111 4"
b0 3"
bx 2"
bx 1"
b10 0"
bx /"
b0 ."
b1 -"
bx ,"
b10 +"
bx *"
b0 )"
b1 ("
bx '"
0&"
x%"
x$"
x#"
bx ""
bx !"
b0 ~
bx }
bx |
bx {
bx z
bx0 m
bx l
bx0 k
b1111 j
b0 i
0h
bx g
0f
b0 e
b1111 d
b0 c
b10 b
bx a
b0 `
b1 _
bx ^
b10 ]
bx \
b0 [
b1 Z
bx Y
b0 X
xW
xV
xU
b0 T
b1111 S
0R
b0 Q
0P
0O
0N
0M
b0 L
b0 K
0J
bx E
bx D
xC
xB
bx A
bx @
x?
x>
bx =
x<
bx0 ;
x:
x9
x8
bx 7
bx 6
x5
x4
x3
bx 2
x1
00
bx0 /
x.
b0 -
x,
x+
x*
x)
b1111 (
0'
b10 &
b0 %
b1 $
b10 #
b0 "
b1 !
$end
#5000
b0 /
b0 k
b0 6"
19"
0#"
0U
0+
0$"
0V
1C
0,
0%"
0W
04
b0 ;
b0 m
b0 8"
05
01
b100 Q"
b0 P"
08
0>
0<
0B
b0 !"
b0 ""
b0 D
b0 \
b0 *"
b0 {
b0 E
b0 Y
b0 '"
b0 z
b0 @
b0 a
b0 /"
b0 }
b0 A
b0 ^
b0 ,"
b0 |
09
03
0)
1?
0*
0:
0.
b0 M"
0O"
b0 2
b0 2"
b0 E"
b0 =
b0 1"
b0 G"
b0 L"
b0 N"
b0 F"
b0 H"
b0 I"
b0 J"
1J
#10000
0J
#15000
1J
#20000
0J
#25000
1J
#30000
0J
#35000
1N
1J
#40000
0J
#45000
1J
#50000
0J
#55000
1J
#60000
0J
#65000
b1 ~
1P
1J
#70000
0J
#75000
b1 K"
1$"
0C
1V
18
1>
b1 !"
b100 Q"
b10101010101010100000000000000000 P"
b10 ~
b10101010101010100000000000000000 -
b10101010101010100000000000000000 c
b10101010101010100000000000000000 3"
b10101010101010100000000000000000 Q
b10101010101010100000000000000000 i
1R
0P
1J
#80000
0J
#85000
b11 ~
b10 K"
15"
1h
1+
1'
0$"
0V
1,
0>
b10 !"
0?
1*
b1 M"
1J
#90000
0J
#95000
b100 Q"
b10101010101010100000000000000000 P"
b10101010101010100000000000000000 7
b10101010101010100000000000000000 g
b10101010101010100000000000000000 6
b10101010101010100000000000000000 l
b10101010101010100000000000000000 7"
0+
0,
1%"
1W
b1 N"
b100 J"
0*
1:
b10 M"
b1 ""
1<
b11 !"
b0 K"
b0 ~
05"
0h
0'
0R
1J
#100000
0J
#105000
1C
0%"
0W
08
0<
b0 !"
1)
1?
0:
b0 M"
1J
#110000
0J
#115000
0)
1J
#120000
0J
#125000
b100 ~
1O
1J
#130000
0J
#135000
b11 K"
1#"
1U
18
1B
b100 !"
b101 ~
1M
0O
1J
#140000
0J
#145000
b0 ~
b0 K"
1&"
1f
0#"
0U
10
0C
14
15
11
0B
b101 !"
0?
1.
b11 M"
1J
#150000
0J
#155000
bx 7
bx g
bx 6
bx l
bx 7"
1C
05
01
04
b1 L"
b100 I"
1?
0.
b0 M"
13
08
b0 !"
b0 K"
b0 ~
0&"
0f
00
0M
1J
#160000
0J
#165000
03
1J
#170000
0J
#175000
b0 ""
b11 @
b11 a
b11 /"
b11 }
b1000000 A
b1000000 ^
b1000000 ,"
b1000000 |
b1 ~
1P
b11 L
b11 e
b1000000 K
b1000000 X
1J
#180000
0J
#185000
b1 K"
1$"
0C
1V
18
1>
b1 !"
b100 Q"
b10111011101110110000000000000000 P"
b10 ~
b10111011101110110000000000000000 -
b10111011101110110000000000000000 c
b10111011101110110000000000000000 3"
b10111011101110110000000000000000 Q
b10111011101110110000000000000000 i
1R
0P
1J
#190000
0J
#195000
b100 Q"
b10111011101110110000000000000000 P"
15"
1h
0$"
0V
1'
1,
b0 N"
b11 H"
b1000000 J"
0?
1*
b1 M"
0>
b10 !"
1J
#200000
0J
#205000
b1 ""
b1 N"
b1000100 J"
b100 Q"
b10111011101110110000000000000001 P"
b10111011101110110000000000000001 -
b10111011101110110000000000000001 c
b10111011101110110000000000000001 3"
b10111011101110110000000000000001 Q
b10111011101110110000000000000001 i
1J
